{
  "surgery": "Tonsill",
  "features": "librosa_mfcc_spectral_106dim",
  "model_type": "mlp",
  "target_session": "2",
  "k_folds": 5,
  "n_crops": 10,
  "feat_dim": 106,
  "hyperparams": {
    "lr": 0.0001,
    "hidden_dim": 128,
    "n_blocks": 1,
    "dropout": 0.5,
    "weight_decay": 0.1,
    "noise_scale": 0.02,
    "n_aug": 5,
    "mixup_alpha": 0.2,
    "crop_sec": 3.0
  },
  "split": {
    "cv_pool": [
      "Tonsill_ses1_speech_0007",
      "Tonsill_ses1_speech_0011",
      "Tonsill_ses1_speech_0026",
      "Tonsill_ses1_speech_0042",
      "Tonsill_ses1_speech_0045",
      "Tonsill_ses1_speech_0062",
      "Tonsill_ses1_speech_0063",
      "Tonsill_ses1_speech_0078",
      "Tonsill_ses1_speech_0080",
      "Tonsill_ses1_speech_0081",
      "Tonsill_ses1_speech_0087",
      "Tonsill_ses1_speech_0089",
      "Tonsill_ses1_speech_0092",
      "Tonsill_ses1_speech_0099",
      "Tonsill_ses1_speech_0108",
      "Tonsill_ses1_speech_0110",
      "Tonsill_ses1_speech_0112",
      "Tonsill_ses1_speech_0122",
      "Tonsill_ses1_speech_0129",
      "Tonsill_ses1_speech_0132",
      "Tonsill_ses1_speech_0137",
      "Tonsill_ses1_speech_0144",
      "Tonsill_ses1_speech_0145"
    ],
    "test": [
      "Tonsill_ses1_speech_0085",
      "Tonsill_ses1_speech_0109",
      "Tonsill_ses1_speech_0111",
      "Tonsill_ses1_speech_0125",
      "Tonsill_ses1_speech_0147"
    ]
  },
  "cv_val_sim": {
    "mean": 0.45416385531425474,
    "std": 0.03726050184941301
  },
  "fold_best_epochs": [
    58,
    124,
    72,
    124,
    31
  ],
  "final_model_epochs": 100,
  "summary": {
    "baseline": 0.5099205136299133,
    "mean_shift": 0.5212304711341857,
    "ensemble": 0.5480473279953003,
    "delta": 0.03812681436538701
  },
  "per_patient_test": [
    {
      "name": "Tonsill_ses1_speech_0085",
      "baseline": 0.6289718151092529,
      "mean_shift": 0.6424965858459473,
      "ensemble": 0.6565332412719727
    },
    {
      "name": "Tonsill_ses1_speech_0109",
      "baseline": 0.1702902913093567,
      "mean_shift": 0.20522600412368774,
      "ensemble": 0.19498014450073242
    },
    {
      "name": "Tonsill_ses1_speech_0111",
      "baseline": 0.5005079507827759,
      "mean_shift": 0.6225870251655579,
      "ensemble": 0.6294992566108704
    },
    {
      "name": "Tonsill_ses1_speech_0125",
      "baseline": 0.5314087867736816,
      "mean_shift": 0.46921032667160034,
      "ensemble": 0.5422949194908142
    },
    {
      "name": "Tonsill_ses1_speech_0147",
      "baseline": 0.7184237241744995,
      "mean_shift": 0.6666324138641357,
      "ensemble": 0.7169290781021118
    }
  ]
}